README.txt
setup.py
numerics/__init__.py
numerics/bar.py
numerics/cal.py
numerics/cat_columns.py
numerics/check.py
numerics/chunk.py
numerics/cleanse.py
numerics/cli.py
numerics/conformity.py
numerics/convert.py
numerics/csvwriter.py
numerics/data.py
numerics/fields.py
numerics/filters.py
numerics/formatting.py
numerics/gather.py
numerics/gaussian.py
numerics/generate.py
numerics/histogram.py
numerics/interpolation.py
numerics/manipulate.py
numerics/mean.py
numerics/median.py
numerics/normalize.py
numerics/parse_date.py
numerics/plot.py
numerics/read.py
numerics/reduce.py
numerics/smooth.py
numerics/sort.py
numerics/split_table.py
numerics/sum.py
numerics/table.py
numerics/text_display.py
numerics/web.py
numerics/write.py
numerics.egg-info/PKG-INFO
numerics.egg-info/SOURCES.txt
numerics.egg-info/dependency_links.txt
numerics.egg-info/entry_points.txt
numerics.egg-info/not-zip-safe
numerics.egg-info/requires.txt
numerics.egg-info/top_level.txt