Metadata-Version: 1.0
Name: numerics
Version: 0.2
Summary: personal experiments in numerics + plotting
Home-page: http://k0s.org/hg/numerics
Author: Jeff Hammel
Author-email: k0scist@gmail.com
License: UNKNOWN
Platform: UNKNOWN
